clarusui/__init__.py
clarusui/alert.html
clarusui/alert.py
clarusui/anchor.html
clarusui/base.html
clarusui/base_content.html
clarusui/card.html
clarusui/card.py
clarusui/chart.html
clarusui/chart.py
clarusui/collapsible.html
clarusui/collapsible.py
clarusui/detailcard.html
clarusui/div.html
clarusui/gridvisualisationelement.py
clarusui/header.html
clarusui/iframe.html
clarusui/iframe.py
clarusui/layout.html
clarusui/layout.py
clarusui/layout_responsive.html
clarusui/messagepanel.py
clarusui/popover.html
clarusui/statsgrid.html
clarusui/style.py
clarusui/table.html
clarusui/table.py
clarusui/table_mobile_responsive.html
clarusui/tabs.html
clarusui/templates.py
clarusui/utils.py
clarusui-0.423.dist-info/METADATA
clarusui-0.423.dist-info/WHEEL
clarusui-0.423.dist-info/top_level.txt
clarusui-0.423.dist-info/RECORD
